MANIFEST.in
README.md
requirements.txt
setup.py
django_werkzeug/__init__.py
django_werkzeug.egg-info/PKG-INFO
django_werkzeug.egg-info/SOURCES.txt
django_werkzeug.egg-info/dependency_links.txt
django_werkzeug.egg-info/not-zip-safe
django_werkzeug.egg-info/requires.txt
django_werkzeug.egg-info/top_level.txt
django_werkzeug/management/__init__.py
django_werkzeug/management/commands/__init__.py
django_werkzeug/management/commands/runserver.py
django_werkzeug/management/commands/runserver_classic.py